README.rst
setup.py
Frcwp/Frcwp.py
Frcwp/__init__.py
Frcwp/distince.py
Frcwp/reshapedata.py
Frcwp/slicing.py
Frcwp.egg-info/PKG-INFO
Frcwp.egg-info/SOURCES.txt
Frcwp.egg-info/dependency_links.txt
Frcwp.egg-info/top_level.txt
Frcwp.egg-info/zip-safe