Metadata-Version: 1.1
Name: Frcwp
Version: 0.0.7
Summary: recognize the outliers of the data set
Home-page: https://github.com/sladesha/Frcwp
Author: sladesal
Author-email: stw386@sina.com
License: MIT
Keywords: algorithm
Platform: UNKNOWN
Classifier: License :: OSI Approved :: MIT License
Classifier: Programming Language :: Python
Classifier: Intended Audience :: Developers
Classifier: Operating System :: OS Independent
